LICENSE
MANIFEST.in
README.rst
setup.py
blogging/__init__.py
blogging/admin.py
blogging/cms_app.py
blogging/cms_plugins.py
blogging/create_class.py
blogging/forms.py
blogging/models.py
blogging/tag_lib.py
blogging/tests.py
blogging/urls.py
blogging/utils.py
blogging/views.py
blogging/widgets.py
blogging/wrapper.py
blogging/custom/__init__.py
blogging/custom/article.py
blogging/custom/defaultblog.py
blogging/custom/defaultsection.py
blogging/custom/section.py
blogging/fixtures/fixtures.json
blogging/static/js/blogging/add_form.js
blogging/templates/blogging/author.html
blogging/templates/blogging/base.html
blogging/templates/blogging/base.html~
blogging/templates/blogging/contact_page.html
blogging/templates/blogging/content_type.html
blogging/templates/blogging/create_page.html
blogging/templates/blogging/create_post.html
blogging/templates/blogging/detail.html
blogging/templates/blogging/detail.html~
blogging/templates/blogging/formpopup.html
blogging/templates/blogging/inline_field.html
blogging/templates/blogging/section.html
blogging/templates/blogging/table_inline_formset.html
blogging/templates/blogging/teaser.html
blogging/templates/blogging/type_form.html
blogging/templates/blogging/includes/add_content_type.html
blogging/templates/blogging/includes/breadcrumb.html
blogging/templates/blogging/includes/contact.html
blogging/templates/blogging/includes/section_view.html
blogging/templates/blogging/includes/teaser_list.html
blogging/templates/blogging/includes/teaser_stack.html
blogging/templates/blogging/includes/teaser_view.html
blogging/templates/blogging/plugin/plugin_author.html
blogging/templates/blogging/plugin/plugin_contact.html
blogging/templates/blogging/plugin/plugin_section.html
blogging/templates/blogging/plugin/plugin_teaser.html
blogging/templates/blogging/plugin/sidebar_list.html
blogging/templates/blogging/plugin/teaser_list.html
blogging/templates/blogging/templatetags/render_content.html
blogging/templatetags/__init__.py
pi_blogging.egg-info/PKG-INFO
pi_blogging.egg-info/SOURCES.txt
pi_blogging.egg-info/dependency_links.txt
pi_blogging.egg-info/requires.txt
pi_blogging.egg-info/top_level.txt