Metadata-Version: 1.1
Name: pi-blogging
Version: 0.1.0b1
Summary: A Simple Blogging App that enables you to create content and content types from frontend itself.
Home-page: https://github.com/PirateLearner/blogging
Author: ['Abhishek Rai', 'Anshul Thakur']
Author-email: ['captain@piratelearner.com']
License: GPL v2
Download-URL: https://github.com/PirateLearner/blogging/archive/0.1.1-beta.tar.gz
Platform: UNKNOWN
Classifier: Environment :: Web Environment
Classifier: Framework :: Django
Classifier: Intended Audience :: Developers
Classifier: License :: OSI Approved :: GNU General Public License v2 or later (GPLv2+)
Classifier: Operating System :: OS Independent
Classifier: Programming Language :: Python
Classifier: Programming Language :: Python :: 2.7
Classifier: Topic :: Internet :: WWW/HTTP
Classifier: Topic :: Internet :: WWW/HTTP :: Dynamic Content
